reclaimed/__init__.py
reclaimed/__main__.py
reclaimed/cli.py
reclaimed/version.py
reclaimed/core/__init__.py
reclaimed/core/cache.py
reclaimed/core/errors.py
reclaimed/core/scanner.py
reclaimed/core/types.py
reclaimed/io/__init__.py
reclaimed/io/filesystem.py
reclaimed/metrics/__init__.py
reclaimed/metrics/buffer.py
reclaimed/metrics/collector.py
reclaimed/metrics/publisher.py
reclaimed/metrics/subscriber.py
reclaimed/metrics/types.py
reclaimed/metrics/utils.py
reclaimed/ui/__init__.py
reclaimed/ui/formatters.py
reclaimed/ui/styles.py
reclaimed/ui/textual_app.py
reclaimed/utils/__init__.py
reclaimed/utils/formatters.py
reclaimed/utils/whitespace.py
reclaimed-0.2.9.dist-info/licenses/LICENSE
reclaimed-0.2.9.dist-info/METADATA
reclaimed-0.2.9.dist-info/WHEEL
reclaimed-0.2.9.dist-info/entry_points.txt
reclaimed-0.2.9.dist-info/top_level.txt
reclaimed-0.2.9.dist-info/RECORD
