Metadata-Version: 2.4
Name: reclaimed
Version: 0.2.9
Summary: A powerful disk usage analyzer with iCloud support
Author-email: Taylor Wilsdon <taylor@taylorwilsdon.com>
Project-URL: Homepage, https://github.com/taylorwilsdon/reclaimed
Project-URL: Repository, https://github.com/taylorwilsdon/reclaimed.git
Project-URL: Issues, https://github.com/taylorwilsdon/reclaimed/issues
Keywords: disk,storage,analyzer,icloud,cli
Classifier: Development Status :: 4 - Beta
Classifier: Environment :: Console
Classifier: Intended Audience :: End Users/Desktop
Classifier: License :: OSI Approved :: MIT License
Classifier: Operating System :: MacOS :: MacOS X
Classifier: Operating System :: POSIX :: Linux
Classifier: Programming Language :: Python :: 3
Classifier: Programming Language :: Python :: 3.8
Classifier: Programming Language :: Python :: 3.9
Classifier: Programming Language :: Python :: 3.10
Classifier: Programming Language :: Python :: 3.11
Classifier: Topic :: System :: Systems Administration
Classifier: Topic :: Utilities
Requires-Python: >=3.8
License-File: LICENSE
Requires-Dist: click>=8.0.0
Requires-Dist: rich>=10.0.0
Requires-Dist: textual>=0.52.1
Requires-Dist: typing_extensions>=4.12.2
Dynamic: license-file
